MANIFEST.in
picard.desktop
setup.cfg
setup.py
picard/__init__.py
picard/album.py
picard/cluster.py
picard/collection.py
picard/config.py
picard/config_upgrade.py
picard/dataobj.py
picard/disc.py
picard/file.py
picard/i18n.py
picard/log.py
picard/mbjson.py
picard/metadata.py
picard/oauth.py
picard/plugin.py
picard/releasegroup.py
picard/resources.py
picard/script.py
picard/similarity.py
picard/tagger.py
picard/track.py
picard/acoustid/__init__.py
picard/acoustid/json_helpers.py
picard/acoustid/manager.py
picard/browser/__init__.py
picard/browser/browser.py
picard/browser/filelookup.py
picard/const/__init__.py
picard/const/attributes.py
picard/const/countries.py
picard/const/languages.py
picard/const/locales.py
picard/coverart/__init__.py
picard/coverart/image.py
picard/coverart/utils.py
picard/coverart/providers/__init__.py
picard/coverart/providers/amazon.py
picard/coverart/providers/caa.py
picard/coverart/providers/caa_release_group.py
picard/coverart/providers/local.py
picard/coverart/providers/whitelist.py
picard/formats/__init__.py
picard/formats/apev2.py
picard/formats/asf.py
picard/formats/id3.py
picard/formats/mp4.py
picard/formats/vorbis.py
picard/formats/wav.py
picard/formats/mutagenext/__init__.py
picard/formats/mutagenext/compatid3.py
picard/formats/mutagenext/tak.py
picard/plugins/__init__.py
picard/ui/__init__.py
picard/ui/cdlookup.py
picard/ui/collectionmenu.py
picard/ui/coverartbox.py
picard/ui/edittagdialog.py
picard/ui/filebrowser.py
picard/ui/infodialog.py
picard/ui/infostatus.py
picard/ui/item.py
picard/ui/itemviews.py
picard/ui/logview.py
picard/ui/mainwindow.py
picard/ui/metadatabox.py
picard/ui/passworddialog.py
picard/ui/ratingwidget.py
picard/ui/searchdialog.py
picard/ui/sortablecheckboxlist.py
picard/ui/tagsfromfilenames.py
picard/ui/ui_cdlookup.py
picard/ui/ui_edittagdialog.py
picard/ui/ui_infodialog.py
picard/ui/ui_infostatus.py
picard/ui/ui_options.py
picard/ui/ui_options_about.py
picard/ui/ui_options_advanced.py
picard_dev.egg-info/PKG-INFO
picard_dev.egg-info/SOURCES.txt
picard_dev.egg-info/dependency_links.txt
picard_dev.egg-info/requires.txt
picard_dev.egg-info/top_level.txt
