Metadata-Version: 1.1
Name: picard-dev
Version: 2.0.0a1500724561
Summary: The next generation MusicBrainz tagger
Home-page: https://picard.musicbrainz.org/
Author: UNKNOWN
Author-email: UNKNOWN
License: UNKNOWN
Keywords: MusicBrainz metadata tagger picard
Platform: UNKNOWN
Classifier: License :: OSI Approved :: GNU General Public License v2 or later (GPLv2+)
Classifier: Development Status :: 3 - Alpha
Classifier: Programming Language :: Python :: 3.5
Classifier: Programming Language :: Python :: 3.6
Classifier: Operating System :: Microsoft :: Windows
Classifier: Operating System :: MacOS
Classifier: Operating System :: POSIX :: Linux
Classifier: Topic :: Multimedia :: Sound/Audio
Classifier: Topic :: Multimedia :: Sound/Audio :: Analysis
